pf/__init__.py
pf/_base.py
pf/_struct.py
pf/_utils.py
pf/constants.py
pf/exceptions.py
pf/filter.py
pf/lib.py
pf/queue.py
pf/rule.py
pf/state.py
pf/status.py
pf/table.py
pf/tests/__init__.py
pf/tests/cmd.py
pf/tests/test_filter.py
py_pf-0.2.3.dist-info/LICENSE.md
py_pf-0.2.3.dist-info/METADATA
py_pf-0.2.3.dist-info/WHEEL
py_pf-0.2.3.dist-info/top_level.txt
py_pf-0.2.3.dist-info/RECORD
